[
  {
    "name": "kitchen",
    "lighting": [
      {
        "name": "main",
        "colors": []
      },
      {
        "name": "counter led 1",
        "colors": [
          "red",
          "green",
          "blue"
        ]
      },
      {
        "name": "counter led 2",
        "colors": [
          "red",
          "green",
          "blue"
        ]
      }
    ],
    "devices": [
      "dishwasher",
      "fridge",
      "cooker"
    ]
  },
  {
    "name": "bathroom",
    "lighting": [
      {
        "name": "main",
        "colors": []
      },
      {
        "name": "mirror led",
        "colors": [
          "warm white",
          "cool white"
        ]
      }
    ],
    "devices": [
      "washing machine",
      "dryer"
    ]
  },
  {
    "name": "dining room",
    "lighting": [
      {
        "name": "main",
        "colors": []
      },
      {
        "name": "wet bar led",
        "colors": [
          "warm white",
          "cool white"
        ]
      }
    ],
    "devices": [
      "squeezer"
    ]
  },
  {
    "name": "porch",
    "lighting": [
      {
        "name": "main",
        "colors": []
      }
    ],
    "devices": [
    ]
  },
  {
    "name": "corridor",
    "lighting": [
      {
        "name": "main",
        "colors": []
      },
      {
        "name": "stairs led",
        "colors": [
          "warm white",
          "cool white"
        ]
      },
      {
        "name": "mirror led",
        "colors": [
          "warm white",
          "cool white"
        ]
      }
    ],
    "devices": [
    ]
  },
  {
    "name": "pantry",
    "lighting": [
      {
        "name": "main",
        "colors": []
      }
    ],
    "devices": [
      "fridge",
      "air conditioning"
    ]
  },
  {
    "name": "utility room",
    "lighting": [
      {
        "name": "main",
        "colors": []
      }
    ],
    "devices": [
      "boiler"
    ]
  },
  {
    "name": "living room",
    "lighting": [
      {
        "name": "main",
        "colors": []
      },
      {
        "name": "tv led",
        "colors": [
          "red",
          "green",
          "blue"
        ]
      },
      {
        "name": "sofa led",
        "colors": [
          "red",
          "green",
          "blue"
        ]
      }
    ],
    "devices": [
      "tv",
      "dvd player",
      "stereo speakers",
      "pc",
      "printer"
    ]
  },
  {
    "name": "bedroom",
    "lighting": [
      {
        "name": "main",
        "colors": []
      },
      {
        "name": "bed led",
        "colors": [
          "red",
          "green",
          "blue"
        ]
      },
      {
        "name": "wardrobe led",
        "colors": [
          "warm white",
          "cool white"
        ]
      }
    ],
    "devices": [
      "iron",
      "tv"
    ]
  },
  {
    "name": "garage",
    "lighting": [
      {
        "name": "main",
        "colors": []
      }
    ],
    "devices": [
      "garage door"
    ]
  },
  {
    "name": "outdoor",
    "lighting": [
      {
        "name": "main",
        "colors": []
      },
      {
        "name": "garden light 1",
        "colors": [
          "warm white",
          "cool white"
        ]
      },
      {
        "name": "garden light 2",
        "colors": [
          "warm white",
          "cool white"
        ]
      },
      {
        "name": "garden light 3",
        "colors": [
          "warm white",
          "cool white"
        ]
      }
    ],
    "devices": [
      "water sprinkler 1",
      "water sprinkler 2",
      "water sprinkler 3",
      "water sprinkler 4"
    ]
  }
]